verilator/blinky/blinky_max/top.v
//**************************************************************************
//
//    Copyright (C) 2020  John Winans
//
//    This library is free software; you can redistribute it and/or
//    modify it under the terms of the GNU Lesser General Public
//    License as published by the Free Software Foundation; either
//    version 2.1 of the License, or (at your option) any later version.
//
//    This library is distributed in the hope that it will be useful,
//    but WITHOUT ANY WARRANTY; without even the implied warranty of
//    MERCHANTABILITY or FITNESS FOR A PARTICULAR PURPOSE.  See the GNU
//    Lesser General Public License for more details.
//
//    You should have received a copy of the GNU Lesser General Public
//    License along with this library; if not, write to the Free Software
//    Foundation, Inc., 51 Franklin Street, Fifth Floor, Boston, MA  02110-1301
//    USA
//
//**************************************************************************




/**
* This will blink the four LEDs on the IceStick Evaluation board
* by dividing down the 12MHZ oscillator on the board.
**************************************************************************/
module top (
    input wire clk,				// 12MHZ clock
    output wire led1,
    output wire led2,
    output wire led3,
    output wire led4,
    output wire led5
	);

    reg [24:0] counter = 0;

	// Drive the LEDs from the MSBs of the counter
    assign led1 = counter[20];		// divide by 2MHZ
    assign led2 = counter[21];		// divide by 4MHZ
    assign led3 = counter[22];		// divide by 8MHZ
    assign led4 = counter[23];		// divide by 16MHZ
    assign led5 = counter[24];		// divide by 32MHZ

	// Add 1 to the counter on each rising edge of the clk input signal
    always @ (posedge clk) 
	begin
        counter <= counter + 1;
    end

endmodule

verilator/blinky/blinky_max/wave.vcd
$version Generated by VerilatedVcd $end
$date Fri Mar  4 07:48:37 2022 $end
$timescale 1ps $end

 $scope module TOP $end
  $var wire  1 # clk $end
  $var wire  1 $ led1 $end
  $var wire  1 % led2 $end
  $var wire  1 & led3 $end
  $var wire  1 ' led4 $end
  $var wire  1 ( led5 $end
  $scope module top $end
   $var wire  1 # clk $end
   $var wire 25 ) counter [24:0] $end
   $var wire  1 $ led1 $end
   $var wire  1 % led2 $end
   $var wire  1 & led3 $end
   $var wire  1 ' led4 $end
   $var wire  1 ( led5 $end
  $upscope $end
 $upscope $end
$enddefinitions $end


#1
1#
0$
0%
0&
0'
0(
b0000000000000000000000000 )
#2
#3
#4
#5
#6
0#
#7
#8
#9
#10
#11
1#
b0000000000000000000000001 )
#12
#13
#14
#15
#16
0#
#17
#18
#19
#20
#21
1#
b0000000000000000000000010 )
#22
#23
#24
#25
#26
0#
#27
#28
#29
#30
#31
1#
b0000000000000000000000011 )
#32
#33
#34
#35
#36
0#
#37
#38
#39
#40
#41
1#
b0000000000000000000000100 )
#42
#43
#44
#45
#46
0#
#47
#48
#49
#50
#51
1#
b0000000000000000000000101 )
#52
#53
#54
#55
#56
0#
#57
#58
#59
#60
#61
1#
b0000000000000000000000110 )
#62
#63
#64
#65
#66
0#
#67
#68
#69
#70
#71
1#
b0000000000000000000000111 )
#72
#73
#74
#75
#76
0#
#77
#78
#79
#80
#81
1#
b0000000000000000000001000 )
#82
#83
#84
#85
#86
0#
#87
#88
#89
#90
#91
1#
b0000000000000000000001001 )
#92
#93
#94
#95
#96
0#
#97
#98
#99
#100
#101
1#
b0000000000000000000001010 )
#102
#103
#104
#105
#106
0#
#107
#108
#109
#110
#111
1#
b0000000000000000000001011 )
#112
#113
#114
#115
#116
0#
#117
#118
#119
#120
#121
1#
b0000000000000000000001100 )
#122
#123
#124
#125
#126
0#
#127
#128
#129
#130
#131
1#
b0000000000000000000001101 )
#132
#133
#134
#135
#136
0#
#137
#138
#139
#140
#141
1#
b0000000000000000000001110 )
#142
#143
#144
#145
#146
0#
#147
#148
#149
#150
#151
1#
b0000000000000000000001111 )
#152
#153
#154
#155
#156
0#
#157
#158
#159
#160
#161
1#
b0000000000000000000010000 )
#162
#163
#164
#165
#166
0#
#167
#168
#169
#170
#171
1#
b0000000000000000000010001 )
#172
#173
#174
#175
#176
0#
#177
#178
#179
#180
#181
1#
b0000000000000000000010010 )
#182
#183
#184
#185
#186
0#
#187
#188
#189
#190
#191
1#
b0000000000000000000010011 )
#192
#193
#194
#195
#196
0#
#197
#198
#199
#200
#201
1#
b0000000000000000000010100 )
#202
#203
#204
#205
#206
0#
#207
#208
#209
#210
#211
1#
b0000000000000000000010101 )
#212
#213
#214
#215
#216
0#
#217
#218
#219
#220
#221
1#
b0000000000000000000010110 )
#222
#223
#224
#225
#226
0#
#227
#228
#229
#230
#231
1#
b0000000000000000000010111 )
#232
#233
#234
#235
#236
0#
#237
#238
#239
#240
#241
1#
b0000000000000000000011000 )
#242
#243
#244
#245
#246
0#
#247
#248
#249
#250
#251
1#
b0000000000000000000011001 )
#252
#253
#254
#255
#256
0#
#257
#258
#259
#260
#261
1#
b0000000000000000000011010 )
#262
#263
#264
#265
#266
0#
#267
#268
#269
#270
#271
1#
b0000000000000000000011011 )
#272
#273
#274
#275
#276
0#
#277
#278
#279
#280
#281
1#
b0000000000000000000011100 )
#282
#283
#284
#285
#286
0#
#287
#288
#289
#290
#291
1#
b0000000000000000000011101 )
#292
#293
#294
#295
#296
0#
#297
#298
#299
#300
#301
1#
b0000000000000000000011110 )
#302
#303
#304
#305
#306
0#
#307
#308
#309
#310
#311
1#
b0000000000000000000011111 )
#312
#313
#314
#315
#316
0#
#317
#318
#319
#320
#321
1#
b0000000000000000000100000 )
#322
#323
#324
#325
#326
0#
#327
#328
#329
#330
#331
1#
b0000000000000000000100001 )
#332
#333
#334
#335
#336
0#
#337
#338
#339
#340
#341
1#
b0000000000000000000100010 )
#342
#343
#344
#345
#346
0#
#347
#348
#349
#350
#351
1#
b0000000000000000000100011 )
#352
#353
#354
#355
#356
0#
#357
#358
#359
#360
#361
1#
b0000000000000000000100100 )
#362
#363
#364
#365
#366
0#
#367
#368
#369
#370
#371
1#
b0000000000000000000100101 )
#372
#373
#374
#375
#376
0#
#377
#378
#379
#380
#381
1#
b0000000000000000000100110 )
#382
#383
#384
#385
#386
0#
#387
#388
#389
#390
#391
1#
b0000000000000000000100111 )
#392
#393
#394
#395
#396
0#
#397
#398
#399
#400
#401
1#
b0000000000000000000101000 )
#402
#403
#404
#405
#406
0#
#407
#408
#409
#410
#411
1#
b0000000000000000000101001 )
#412
#413
#414
#415
#416
0#
#417
#418
#419
#420
#421
1#
b0000000000000000000101010 )
#422
#423
#424
#425
#426
0#
#427
#428
#429
#430
#431
1#
b0000000000000000000101011 )
#432
#433
#434
#435
#436
0#
#437
#438
#439
#440
#441
1#
b0000000000000000000101100 )
#442
#443
#444
#445
#446
0#
#447
#448
#449
#450
#451
1#
b0000000000000000000101101 )
#452
#453
#454
#455
#456
0#
#457
#458
#459
#460
#461
1#
b0000000000000000000101110 )
#462
#463
#464
#465
#466
0#
#467
#468
#469
#470
#471
1#
b0000000000000000000101111 )
#472
#473
#474
#475
#476
0#
#477
#478
#479
#480
#481
1#
b0000000000000000000110000 )
#482
#483
#484
#485
#486
0#
#487
#488
#489
#490
#491
1#
b0000000000000000000110001 )
#492
#493
#494
#495
#496
0#
#497
#498
#499
#500
#501
1#
b0000000000000000000110010 )
#502
#503
#504
#505
#506
0#
#507
#508
#509
#510
#511
1#
b0000000000000000000110011 )
#512
#513
#514
#515
#516
0#
#517
#518
#519
#520
#521
1#
b0000000000000000000110100 )
#522
#523
#524
#525
#526
0#
#527
#528
#529
#530
#531
1#
b0000000000000000000110101 )
#532
#533
#534
#535
#536
0#
#537
#538
#539
#540
#541
1#
b0000000000000000000110110 )
#542
#543
#544
#545
#546
0#
#547
#548
#549
#550
#551
1#
b0000000000000000000110111 )
#552
#553
#554
#555
#556
0#
#557
#558
#559
#560
#561
1#
b0000000000000000000111000 )
#562
#563
#564
#565
#566
0#
#567
#568
#569
#570
#571
1#
b0000000000000000000111001 )
#572
#573
#574
#575
#576
0#
#577
#578
#579
#580
#581
1#
b0000000000000000000111010 )
#582
#583
#584
#585
#586
0#
#587
#588
#589
#590
#591
1#
b0000000000000000000111011 )
#592
#593
#594
#595
#596
0#
#597
#598
#599
#600
#601
1#
b0000000000000000000111100 )
#602
#603
#604
#605
#606
0#
#607
#608
#609
#610
#611
1#
b0000000000000000000111101 )
#612
#613
#614
#615
#616
0#
#617
#618
#619
#620
#621
1#
b0000000000000000000111110 )
#622
#623
#624
#625
#626
0#
#627
#628
#629
#630
#631
1#
b0000000000000000000111111 )
#632
#633
#634
#635
#636
0#
#637
#638
#639
#640
#641
1#
b0000000000000000001000000 )
#642
#643
#644
#645
#646
0#
#647
#648
#649
#650
#651
1#
b0000000000000000001000001 )
#652
#653
#654
#655
#656
0#
#657
#658
#659
#660
#661
1#
b0000000000000000001000010 )
#662
#663
#664
#665
#666
0#
#667
#668
#669
#670
#671
1#
b0000000000000000001000011 )
#672
#673
#674
#675
#676
0#
#677
#678
#679
#680
#681
1#
b0000000000000000001000100 )
#682
#683
#684
#685
#686
0#
#687
#688
#689
#690
#691
1#
b0000000000000000001000101 )
#692
#693
#694
#695
#696
0#
#697
#698
#699
#700
#701
1#
b0000000000000000001000110 )
#702
#703
#704
#705
#706
0#
#707
#708
#709
#710
#711
1#
b0000000000000000001000111 )
#712
#713
#714
#715
#716
0#
#717
#718
#719
#720
#721
1#
b0000000000000000001001000 )
#722
#723
#724
#725
#726
0#
#727
#728
#729
#730
#731
1#
b0000000000000000001001001 )
#732
#733
#734
#735
#736
0#
#737
#738
#739
#740
#741
1#
b0000000000000000001001010 )
#742
#743
#744
#745
#746
0#
#747
#748
#749
#750
#751
1#
b0000000000000000001001011 )
#752
#753
#754
#755
#756
0#
#757
#758
#759
#760
#761
1#
b0000000000000000001001100 )
#762
#763
#764
#765
#766
0#
#767
#768
#769
#770
#771
1#
b0000000000000000001001101 )
#772
#773
#774
#775
#776
0#
#777
#778
#779
#780
#781
1#
b0000000000000000001001110 )
#782
#783
#784
#785
#786
0#
#787
#788
#789
#790
#791
1#
b0000000000000000001001111 )
#792
#793
#794
#795
#796
0#
#797
#798
#799
#800
#801
1#
b0000000000000000001010000 )
#802
#803
#804
#805
#806
0#
#807
#808
#809
#810
#811
1#
b0000000000000000001010001 )
#812
#813
#814
#815
#816
0#
#817
#818
#819
#820
#821
1#
b0000000000000000001010010 )
#822
#823
#824
#825
#826
0#
#827
#828
#829
#830
#831
1#
b0000000000000000001010011 )
#832
#833
#834
#835
#836
0#
#837
#838
#839
#840
#841
1#
b0000000000000000001010100 )
#842
#843
#844
#845
#846
0#
#847
#848
#849
#850
#851
1#
b0000000000000000001010101 )
#852
#853
#854
#855
#856
0#
#857
#858
#859
#860
#861
1#
b0000000000000000001010110 )
#862
#863
#864
#865
#866
0#
#867
#868
#869
#870
#871
1#
b0000000000000000001010111 )
#872
#873
#874
#875
#876
0#
#877
#878
#879
#880
#881
1#
b0000000000000000001011000 )
#882
#883
#884
#885
#886
0#
#887
#888
#889
#890
#891
1#
b0000000000000000001011001 )
#892
#893
#894
#895
#896
0#
#897
#898
#899
#900
#901
1#
b0000000000000000001011010 )
#902
#903
#904
#905
#906
0#
#907
#908
#909
#910
#911
1#
b0000000000000000001011011 )
#912
#913
#914
#915
#916
0#
#917
#918
#919
#920
#921
1#
b0000000000000000001011100 )
#922
#923
#924
#925
#926
0#
#927
#928
#929
#930
#931
1#
b0000000000000000001011101 )
#932
#933
#934
#935
#936
0#
#937
#938
#939
#940
#941
1#
b0000000000000000001011110 )
#942
#943
#944
#945
#946
0#
#947
#948
#949
#950
#951
1#
b0000000000000000001011111 )
#952
#953
#954
#955
#956
0#
#957
#958
#959
#960
#961
1#
b0000000000000000001100000 )
#962
#963
#964
#965
#966
0#
#967
#968
#969
#970
#971
1#
b0000000000000000001100001 )
#972
#973
#974
#975
#976
0#
#977
#978
#979
#980
#981
1#
b0000000000000000001100010 )
#982
#983
#984
#985
#986
0#
#987
#988
#989
#990
#991
1#
b0000000000000000001100011 )
#992
#993
#994
#995
#996
0#
#997
#998
#999
#1000
#1001
1#
b0000000000000000001100100 )
#1002
#1003
#1004
#1005
#1006
0#
#1007
#1008
#1009
#1010
#1011
1#
b0000000000000000001100101 )
#1012
#1013
#1014
#1015
#1016
0#
#1017
#1018
#1019
#1020
#1021
1#
b0000000000000000001100110 )
#1022
#1023
#1024
#1025
#1026
0#
#1027
#1028
#1029
#1030
#1031
1#
b0000000000000000001100111 )
#1032
#1033
#1034
#1035
#1036
0#
#1037
#1038
#1039
#1040
#1041
1#
b0000000000000000001101000 )
#1042
#1043
#1044
#1045
#1046
0#
#1047
#1048
#1049
#1050
#1051
1#
b0000000000000000001101001 )
#1052
#1053
#1054
#1055
#1056
0#
#1057
#1058
#1059
#1060
#1061
1#
b0000000000000000001101010 )
#1062
#1063
#1064
#1065
#1066
0#
#1067
#1068
#1069
#1070
#1071
1#
b0000000000000000001101011 )
#1072
#1073
#1074
#1075
#1076
0#
#1077
#1078
#1079
#1080
#1081
1#
b0000000000000000001101100 )
#1082
#1083
#1084
#1085
#1086
0#
#1087
#1088
#1089
#1090
#1091
1#
b0000000000000000001101101 )
#1092
#1093
#1094
#1095
#1096
0#
#1097
#1098
#1099
#1100
#1101
1#
b0000000000000000001101110 )
#1102
#1103
#1104
#1105
#1106
0#
#1107
#1108
#1109
#1110
#1111
1#
b0000000000000000001101111 )
#1112
#1113
#1114
#1115
#1116
0#
#1117
#1118
#1119
#1120
#1121
1#
b0000000000000000001110000 )
#1122
#1123
#1124
#1125
#1126
0#
#1127
#1128
#1129
#1130
#1131
1#
b0000000000000000001110001 )
#1132
#1133
#1134
#1135
#1136
0#
#1137
#1138
#1139
#1140
#1141
1#
b0000000000000000001110010 )
#1142
#1143
#1144
#1145
#1146
0#
#1147
#1148
#1149
#1150
#1151
1#
b0000000000000000001110011 )
#1152
#1153
#1154
#1155
#1156
0#
#1157
#1158
#1159
#1160
#1161
1#
b0000000000000000001110100 )
#1162
#1163
#1164
#1165
#1166
0#
#1167
#1168
#1169
#1170
#1171
1#
b0000000000000000001110101 )
#1172
#1173
#1174
#1175
#1176
0#
#1177
#1178
#1179
#1180
#1181
1#
b0000000000000000001110110 )
#1182
#1183
#1184
#1185
#1186
0#
#1187
#1188
#1189
#1190
#1191
1#
b0000000000000000001110111 )
#1192
#1193
#1194
#1195
#1196
0#
#1197
#1198
#1199
#1200
#1201
1#
b0000000000000000001111000 )
#1202
#1203
#1204
#1205
#1206
0#
#1207
#1208
#1209
#1210
#1211
1#
b0000000000000000001111001 )
#1212
#1213
#1214
#1215
#1216
0#
#1217
#1218
#1219
#1220
#1221
1#
b0000000000000000001111010 )
#1222
#1223
#1224
#1225
#1226
0#
#1227
#1228
#1229
#1230
#1231
1#
b0000000000000000001111011 )
#1232
#1233
#1234
#1235
#1236
0#
#1237
#1238
#1239
#1240
#1241
1#
b0000000000000000001111100 )
#1242
#1243
#1244
#1245
#1246
0#
#1247
#1248
#1249
#1250
#1251
1#
b0000000000000000001111101 )
#1252
#1253
#1254
#1255
#1256
0#
#1257
#1258
#1259
#1260
#1261
1#
b0000000000000000001111110 )
#1262
#1263
#1264
#1265
#1266
0#
#1267
#1268
#1269
#1270
#1271
1#
b0000000000000000001111111 )
#1272
#1273
#1274
#1275
#1276
0#
#1277
#1278
#1279
#1280
#1281
1#
b0000000000000000010000000 )
#1282
#1283
#1284
#1285
#1286
0#
#1287
#1288
#1289
#1290
#1291
1#
b0000000000000000010000001 )
#1292
#1293
#1294
#1295
#1296
0#
#1297
#1298
#1299
#1300
#1301
1#
b0000000000000000010000010 )
#1302
#1303
#1304
#1305
#1306
0#
#1307
#1308
#1309
#1310
#1311
1#
b0000000000000000010000011 )
#1312
#1313
#1314
#1315
#1316
0#
#1317
#1318
#1319
#1320
#1321
1#
b0000000000000000010000100 )
#1322
#1323
#1324
#1325
#1326
0#
#1327
#1328
#1329
#1330
#1331
1#
b0000000000000000010000101 )
#1332
#1333
#1334
#1335
#1336
0#
#1337
#1338
#1339
#1340
#1341
1#
b0000000000000000010000110 )
#1342
#1343
#1344
#1345
#1346
0#
#1347
#1348
#1349
#1350
#1351
1#
b0000000000000000010000111 )
#1352
#1353
#1354
#1355
#1356
0#
#1357
#1358
#1359
#1360
#1361
1#
b0000000000000000010001000 )
#1362
#1363
#1364
#1365
#1366
0#
#1367
#1368
#1369
#1370
#1371
1#
b0000000000000000010001001 )
#1372
#1373
#1374
#1375
#1376
0#
#1377
#1378
#1379
#1380
#1381
1#
b0000000000000000010001010 )
#1382
#1383
#1384
#1385
#1386
0#
#1387
#1388
#1389
#1390
#1391
1#
b0000000000000000010001011 )
#1392
#1393
#1394
#1395
#1396
0#
#1397
#1398
#1399
#1400
#1401
1#
b0000000000000000010001100 )
#1402
#1403
#1404
#1405
#1406
0#
#1407
#1408
#1409
#1410
#1411
1#
b0000000000000000010001101 )
#1412
#1413
#1414
#1415
#1416
0#
#1417
#1418
#1419
#1420
#1421
1#
b0000000000000000010001110 )
#1422
#1423
#1424
#1425
#1426
0#
#1427
#1428
#1429
#1430
#1431
1#
b0000000000000000010001111 )
#1432
#1433
#1434
#1435
#1436
0#
#1437
#1438
#1439
#1440
#1441
1#
b0000000000000000010010000 )
#1442
#1443
#1444
#1445
#1446
0#
#1447
#1448
#1449
#1450
#1451
1#
b0000000000000000010010001 )
#1452
#1453
#1454
#1455
#1456
0#
#1457
#1458
#1459
#1460
#1461
1#
b0000000000000000010010010 )
#1462
#1463
#1464
#1465
#1466
0#
#1467
#1468
#1469
#1470
#1471
1#
b0000000000000000010010011 )
#1472
#1473
#1474
#1475
#1476
0#
#1477
#1478
#1479
#1480
#1481
1#
b0000000000000000010010100 )
#1482
#1483
#1484
#1485
#1486
0#
#1487
#1488
#1489
#1490
#1491
1#
b0000000000000000010010101 )
#1492
#1493
#1494
#1495
#1496
0#
#1497
#1498
#1499
#1500
#1501
1#
b0000000000000000010010110 )
#1502
#1503
#1504
#1505
#1506
0#
#1507
#1508
#1509
#1510
#1511
1#
b0000000000000000010010111 )
#1512
#1513
#1514
#1515
#1516
0#
#1517
#1518
#1519
#1520
#1521
1#
b0000000000000000010011000 )
#1522
#1523
#1524
#1525
#1526
0#
#1527
#1528
#1529
#1530
#1531
1#
b0000000000000000010011001 )
#1532
#1533
#1534
#1535
#1536
0#
#1537
#1538
#1539
#1540
#1541
1#
b0000000000000000010011010 )
#1542
#1543
#1544
#1545
#1546
0#
#1547
#1548
#1549
#1550
#1551
1#
b0000000000000000010011011 )
#1552
#1553
#1554
#1555
#1556
0#
#1557
#1558
#1559
#1560
#1561
1#
b0000000000000000010011100 )
#1562
#1563
#1564
#1565
#1566
0#
#1567
#1568
#1569
#1570
#1571
1#
b0000000000000000010011101 )
#1572
#1573
#1574
#1575
#1576
0#
#1577
#1578
#1579
#1580
#1581
1#
b0000000000000000010011110 )
#1582
#1583
#1584
#1585
#1586
0#
#1587
#1588
#1589
#1590
#1591
1#
b0000000000000000010011111 )
#1592
#1593
#1594
#1595
#1596
0#
#1597
#1598
#1599
#1600
#1601
1#
b0000000000000000010100000 )
#1602
#1603
#1604
#1605
#1606
0#
#1607
#1608
#1609
#1610
#1611
1#
b0000000000000000010100001 )
#1612
#1613
#1614
#1615
#1616
0#
#1617
#1618
#1619
#1620
#1621
1#
b0000000000000000010100010 )
#1622
#1623
#1624
#1625
#1626
0#
#1627
#1628
#1629
#1630
#1631
1#
b0000000000000000010100011 )
#1632
#1633
#1634
#1635
#1636
0#
#1637
#1638
#1639
#1640
#1641
1#
b0000000000000000010100100 )
#1642
#1643
#1644
#1645
#1646
0#
#1647
#1648
#1649
#1650
#1651
1#
b0000000000000000010100101 )
#1652
#1653
#1654
#1655
#1656
0#
#1657
#1658
#1659
#1660
#1661
1#
b0000000000000000010100110 )
#1662
#1663
#1664
#1665
#1666
0#
#1667
#1668
#1669
#1670
#1671
1#
b0000000000000000010100111 )
#1672
#1673
#1674
#1675
#1676
0#
#1677
#1678
#1679
#1680
#1681
1#
b0000000000000000010101000 )
#1682
#1683
#1684
#1685
#1686
0#
#1687
#1688
#1689
#1690
#1691
1#
b0000000000000000010101001 )
#1692
#1693
#1694
#1695
#1696
0#
#1697
#1698
#1699
#1700
#1701
1#
b0000000000000000010101010 )
#1702
#1703
#1704
#1705
#1706
0#
#1707
#1708
#1709
#1710
#1711
1#
b0000000000000000010101011 )
#1712
#1713
#1714
#1715
#1716
0#
#1717
#1718
#1719
#1720
#1721
1#
b0000000000000000010101100 )
#1722
#1723
#1724
#1725
#1726
0#
#1727
#1728
#1729
#1730
#1731
1#
b0000000000000000010101101 )
#1732
#1733
#1734
#1735
#1736
0#
#1737
#1738
#1739
#1740
#1741
1#
b0000000000000000010101110 )
#1742
#1743
#1744
#1745
#1746
0#
#1747
#1748
#1749
#1750
#1751
1#
b0000000000000000010101111 )
#1752
#1753
#1754
#1755
#1756
0#
#1757
#1758
#1759
#1760
#1761
1#
b0000000000000000010110000 )
#1762
#1763
#1764
#1765
#1766
0#
#1767
#1768
#1769
#1770
#1771
1#
b0000000000000000010110001 )
#1772
#1773
#1774
#1775
#1776
0#
#1777
#1778
#1779
#1780
#1781
1#
b0000000000000000010110010 )
#1782
#1783
#1784
#1785
#1786
0#
#1787
#1788
#1789
#1790
#1791
1#
b0000000000000000010110011 )
#1792
#1793
#1794
#1795
#1796
0#
#1797
#1798
#1799
#1800
#1801
1#
b0000000000000000010110100 )
#1802
#1803
#1804
#1805
#1806
0#
#1807
#1808
#1809
#1810
#1811
1#
b0000000000000000010110101 )
#1812
#1813
#1814
#1815
#1816
0#
#1817
#1818
#1819
#1820
#1821
1#
b0000000000000000010110110 )
#1822
#1823
#1824
#1825
#1826
0#
#1827
#1828
#1829
#1830
#1831
1#
b0000000000000000010110111 )
#1832
#1833
#1834
#1835
#1836
0#
#1837
#1838
#1839
#1840
#1841
1#
b0000000000000000010111000 )
#1842
#1843
#1844
#1845
#1846
0#
#1847
#1848
#1849
#1850
#1851
1#
b0000000000000000010111001 )
#1852
#1853
#1854
#1855
#1856
0#
#1857
#1858
#1859
#1860
#1861
1#
b0000000000000000010111010 )
#1862
#1863
#1864
#1865
#1866
0#
#1867
#1868
#1869
#1870
#1871
1#
b0000000000000000010111011 )
#1872
#1873
#1874
#1875
#1876
0#
#1877
#1878
#1879
#1880
#1881
1#
b0000000000000000010111100 )
#1882
#1883
#1884
#1885
#1886
0#
#1887
#1888
#1889
#1890
#1891
1#
b0000000000000000010111101 )
#1892
#1893
#1894
#1895
#1896
0#
#1897
#1898
#1899
#1900
#1901
1#
b0000000000000000010111110 )
#1902
#1903
#1904
#1905
#1906
0#
#1907
#1908
#1909
#1910
#1911
1#
b0000000000000000010111111 )
#1912
#1913
#1914
#1915
#1916
0#
#1917
#1918
#1919
#1920
#1921
1#
b0000000000000000011000000 )
#1922
#1923
#1924
#1925
#1926
0#
#1927
#1928
#1929
#1930
#1931
1#
b0000000000000000011000001 )
#1932
#1933
#1934
#1935
#1936
0#
#1937
#1938
#1939
#1940
#1941
1#
b0000000000000000011000010 )
#1942
#1943
#1944
#1945
#1946
0#
#1947
#1948
#1949
#1950
#1951
1#
b0000000000000000011000011 )
#1952
#1953
#1954
#1955
#1956
0#
#1957
#1958
#1959
#1960
#1961
1#
b0000000000000000011000100 )
#1962
#1963
#1964
#1965
#1966
0#
#1967
#1968
#1969
#1970
#1971
1#
b0000000000000000011000101 )
#1972
#1973
#1974
#1975
#1976
0#
#1977
#1978
#1979
#1980
#1981
1#
b0000000000000000011000110 )
#1982
#1983
#1984
#1985
#1986
0#
#1987
#1988
#1989
#1990
#1991
1#
b0000000000000000011000111 )
#1992
#1993
#1994
#1995
#1996
0#
#1997
#1998
#1999
#2000
#2001
1#
b0000000000000000011001000 )
#2002
#2003
#2004
#2005
#2006
0#
#2007
#2008
#2009
#2010
#2011
1#
b0000000000000000011001001 )
#2012
#2013
#2014
#2015
#2016
0#
#2017
#2018
#2019
#2020
#2021
1#
b0000000000000000011001010 )
#2022
#2023
#2024
#2025
#2026
0#
#2027
#2028
#2029
#2030
#2031
1#
b0000000000000000011001011 )
#2032
#2033
#2034
#2035
#2036
0#
#2037
#2038
#2039
#2040
#2041
1#
b0000000000000000011001100 )
#2042
#2043
#2044
#2045
#2046
0#
#2047
#2048
#2049
#2050
#2051
1#
b0000000000000000011001101 )
#2052
#2053
#2054
#2055
#2056
0#
#2057
#2058
#2059
#2060
#2061
1#
b0000000000000000011001110 )
#2062
#2063
#2064
#2065
#2066
0#
#2067
#2068
#2069
#2070
#2071
1#
b0000000000000000011001111 )
#2072
#2073
#2074
#2075
#2076
0#
#2077
#2078
#2079
#2080
#2081
1#
b0000000000000000011010000 )
#2082
#2083
#2084
#2085
#2086
0#
#2087
#2088
#2089
#2090
#2091
1#
b0000000000000000011010001 )
#2092
#2093
#2094
#2095
#2096
0#
#2097
#2098
#2099
#2100
#2101
1#
b0000000000000000011010010 )
#2102
#2103
#2104
#2105
#2106
0#
#2107
#2108
#2109
#2110
#2111
1#
b0000000000000000011010011 )
#2112
#2113
#2114
#2115
#2116
0#
#2117
#2118
#2119
#2120
#2121
1#
b0000000000000000011010100 )
#2122
#2123
#2124
#2125
#2126
0#
#2127
#2128
#2129
#2130
#2131
1#
b0000000000000000011010101 )
#2132
#2133
#2134
#2135
#2136
0#
#2137
#2138
#2139
#2140
#2141
1#
b0000000000000000011010110 )
#2142
#2143
#2144
#2145
#2146
0#
#2147
#2148
#2149
#2150
#2151
1#
b0000000000000000011010111 )
#2152
#2153
#2154
#2155
#2156
0#
#2157
#2158
#2159
#2160
#2161
1#
b0000000000000000011011000 )
#2162
#2163
#2164
#2165
#2166
0#
#2167
#2168
#2169
#2170
#2171
1#
b0000000000000000011011001 )
#2172
#2173
#2174
#2175
#2176
0#
#2177
#2178
#2179
#2180
#2181
1#
b0000000000000000011011010 )
#2182
#2183
#2184
#2185
#2186
0#
#2187
#2188
#2189
#2190
#2191
1#
b0000000000000000011011011 )
#2192
#2193
#2194
#2195
#2196
0#
#2197
#2198
#2199
#2200
#2201
1#
b0000000000000000011011100 )
#2202
#2203
#2204
#2205
#2206
0#
#2207
#2208
#2209
#2210
#2211
1#
b0000000000000000011011101 )
#2212
#2213
#2214
#2215
#2216
0#
#2217
#2218
#2219
#2220
#2221
1#
b0000000000000000011011110 )
#2222
#2223
#2224
#2225
#2226
0#
#2227
#2228
#2229
#2230
#2231
1#
b0000000000000000011011111 )
#2232
#2233
#2234
#2235
#2236
0#
#2237
#2238
#2239
#2240
#2241
1#
b0000000000000000011100000 )
#2242
#2243
#2244
#2245
#2246
0#
#2247
#2248
#2249
#2250
#2251
1#
b0000000000000000011100001 )
#2252
#2253
#2254
#2255
#2256
0#
#2257
#2258
#2259
#2260
#2261
1#
b0000000000000000011100010 )
#2262
#2263
#2264
#2265
#2266
0#
#2267
#2268
#2269
#2270
#2271
1#
b0000000000000000011100011 )
#2272
#2273
#2274
#2275
#2276
0#
#2277
#2278
#2279
#2280
#2281
1#
b0000000000000000011100100 )
#2282
#2283
#2284
#2285
#2286
0#
#2287
#2288
#2289
#2290
#2291
1#
b0000000000000000011100101 )
#2292
#2293
#2294
#2295
#2296
0#
#2297
#2298
#2299
#2300
#2301
1#
b0000000000000000011100110 )
#2302
#2303
#2304
#2305
#2306
0#
#2307
#2308
#2309
#2310
#2311
1#
b0000000000000000011100111 )
#2312
#2313
#2314
#2315
#2316
0#
#2317
#2318
#2319
#2320
#2321
1#
b0000000000000000011101000 )
#2322
#2323
#2324
#2325
#2326
0#
#2327
#2328
#2329
#2330
#2331
1#
b0000000000000000011101001 )
#2332
#2333
#2334
#2335
#2336
0#
#2337
#2338
#2339
#2340
#2341
1#
b0000000000000000011101010 )
#2342
#2343
#2344
#2345
#2346
0#
#2347
#2348
#2349
#2350
#2351
1#
b0000000000000000011101011 )
#2352
#2353
#2354
#2355
#2356
0#
#2357
#2358
#2359
#2360
#2361
1#
b0000000000000000011101100 )
#2362
#2363
#2364
#2365
#2366
0#
#2367
#2368
#2369
#2370
#2371
1#
b0000000000000000011101101 )
#2372
#2373
#2374
#2375
#2376
0#
#2377
#2378
#2379
#2380
#2381
1#
b0000000000000000011101110 )
#2382
#2383
#2384
#2385
#2386
0#
#2387
#2388
#2389
#2390
#2391
1#
b0000000000000000011101111 )
#2392
#2393
#2394
#2395
#2396
0#
#2397
#2398
#2399
#2400
#2401
1#
b0000000000000000011110000 )
#2402
#2403
#2404
#2405
#2406
0#
#2407
#2408
#2409
#2410
#2411
1#
b0000000000000000011110001 )
#2412
#2413
#2414
#2415
#2416
0#
#2417
#2418
#2419
#2420
#2421
1#
b0000000000000000011110010 )
#2422
#2423
#2424
#2425
#2426
0#
#2427
#2428
#2429
#2430
#2431
1#
b0000000000000000011110011 )
#2432
#2433
#2434
#2435
#2436
0#
#2437
#2438
#2439
#2440
#2441
1#
b0000000000000000011110100 )
#2442
#2443
#2444
#2445
#2446
0#
#2447
#2448
#2449
#2450
#2451
1#
b0000000000000000011110101 )
#2452
#2453
#2454
#2455
#2456
0#
#2457
#2458
#2459
#2460
#2461
1#
b0000000000000000011110110 )
#2462
#2463
#2464
#2465
#2466
0#
#2467
#2468
#2469
#2470
#2471
1#
b0000000000000000011110111 )
#2472
#2473
#2474
#2475
#2476
0#
#2477
#2478
#2479
#2480
#2481
1#
b0000000000000000011111000 )
#2482
#2483
#2484
#2485
#2486
0#
#2487
#2488
#2489
#2490
#2491
1#
b0000000000000000011111001 )
#2492
#2493
#2494
#2495
#2496
0#
#2497
#2498
#2499
#2500
#2501
1#
b0000000000000000011111010 )
#2502
#2503
#2504
#2505
#2506
0#
#2507
#2508
#2509
#2510
#2511
1#
b0000000000000000011111011 )
#2512
#2513
#2514
#2515
#2516
0#
#2517
#2518
#2519
#2520
#2521
1#
b0000000000000000011111100 )
#2522
#2523
#2524
#2525
#2526
0#
#2527
#2528
#2529
#2530
#2531
1#
b0000000000000000011111101 )
#2532
#2533
#2534
#2535
#2536
0#
#2537
#2538
